Workbook

Sheet Price Sheet
A1: Draft starting prices, researched from small-business/local-agency market benchmarks (July 2026). Edit the yellow Suggested Price / Suggested Cost cells to your own numbers, then enter the final values into the Hub's Service Pricing Admin tool. Margin recalculates automatically.
A3: Category | B3: Service | C3: Billing Type | D3: Suggested Price ($) | E3: Suggested Cost ($) | F3: Margin ($) | G3: Notes / Benchmark
A4: Organic Social | B4: Feed Posts (static images, carousels) | C4: Monthly | D4: 350 | E4: 0 | F4: =D4-E4 -> 350
A5: Organic Social | B5: Reels & Short-Form Video | C5: Monthly | D5: 400 | E5: 0 | F5: =D5-E5 -> 400
A6: Organic Social | B6: Stories | C6: Monthly | D6: 150 | E6: 0 | F6: =D6-E6 -> 150
A7: Organic Social | B7: Community Management (responding to comments, DMs, engaging followers) | C7: Monthly | D7: 250 | E7: 0 | F7: =D7-E7 -> 250
A8: Organic Social | B8: Content Calendar Management | C8: Monthly | D8: 200 | E8: 0 | F8: =D8-E8 -> 200
A9: Organic Social | B9: Hashtag Strategy | C9: Monthly | D9: 100 | E9: 0 | F9: =D9-E9 -> 100
A10: Organic Social | B10: Profile Optimization | C10: Monthly | D10: 100 | E10: 0 | F10: =D10-E10 -> 100
A11: Organic Social | B11: Social Listening & Trend Monitoring | C11: Monthly | D11: 150 | E11: 0 | F11: =D11-E11 -> 150
A12: Paid Social | B12: Meta Ads (Facebook + Instagram) | C12: Monthly | D12: 600 | E12: 0 | F12: =D12-E12 -> 600 | G12: Mgmt fee only, excludes ad spend
A13: Paid Social | B13: TikTok Ads | C13: Monthly | D13: 500 | E13: 0 | F13: =D13-E13 -> 500 | G13: Mgmt fee only, excludes ad spend
A14: Paid Social | B14: LinkedIn Ads | C14: Monthly | D14: 600 | E14: 0 | F14: =D14-E14 -> 600 | G14: Mgmt fee only, excludes ad spend
A15: Paid Social | B15: Pinterest Ads | C15: Monthly | D15: 350 | E15: 0 | F15: =D15-E15 -> 350 | G15: Mgmt fee only, excludes ad spend
A16: Paid Social | B16: Snapchat Ads | C16: Monthly | D16: 350 | E16: 0 | F16: =D16-E16 -> 350 | G16: Mgmt fee only, excludes ad spend
A17: Paid Social | B17: Audience Research & Targeting | C17: Monthly | D17: 200 | E17: 0 | F17: =D17-E17 -> 200
A18: Paid Social | B18: Ad Creative Production | C18: Monthly | D18: 300 | E18: 0 | F18: =D18-E18 -> 300
A19: Paid Social | B19: Campaign Setup & Management | C19: One-Time Setup | D19: 500 | E19: 0 | F19: =D19-E19 -> 500
A20: Paid Social | B20: A/B Testing | C20: Monthly | D20: 150 | E20: 0 | F20: =D20-E20 -> 150
A21: Paid Social | B21: Retargeting Campaigns | C21: Monthly | D21: 250 | E21: 0 | F21: =D21-E21 -> 250
A22: Paid Social | B22: Budget Management & Reporting | C22: Monthly | D22: 150 | E22: 0 | F22: =D22-E22 -> 150
A23: Paid Search | B23: Google Ads — Search | C23: Monthly | D23: 700 | E23: 0 | F23: =D23-E23 -> 700 | G23: Mgmt fee only, excludes ad spend
A24: Paid Search | B24: Google Ads — Display | C24: Monthly | D24: 500 | E24: 0 | F24: =D24-E24 -> 500 | G24: Mgmt fee only, excludes ad spend
A25: Paid Search | B25: Google Ads — Performance Max | C25: Monthly | D25: 600 | E25: 0 | F25: =D25-E25 -> 600 | G25: Mgmt fee only, excludes ad spend
A26: Paid Search | B26: Google Ads — Shopping | C26: Monthly | D26: 500 | E26: 0 | F26: =D26-E26 -> 500 | G26: Mgmt fee only, excludes ad spend
A27: Paid Search | B27: Keyword Research | C27: Monthly | D27: 200 | E27: 0 | F27: =D27-E27 -> 200
A28: Paid Search | B28: Ad Copywriting | C28: Monthly | D28: 200 | E28: 0 | F28: =D28-E28 -> 200
A29: Paid Search | B29: Landing Page Recommendations | C29: Monthly | D29: 150 | E29: 0 | F29: =D29-E29 -> 150
A30: Paid Search | B30: Bid Strategy Management | C30: Monthly | D30: 200 | E30: 0 | F30: =D30-E30 -> 200
A31: Paid Search | B31: Conversion Tracking Setup | C31: One-Time Setup | D31: 350 | E31: 0 | F31: =D31-E31 -> 350
A32: Paid Search | B32: Quality Score Optimization | C32: Monthly | D32: 150 | E32: 0 | F32: =D32-E32 -> 150
A33: SEO | B33: On-Page SEO (meta titles, descriptions, headers, content optimization) | C33: Monthly | D33: 400 | E33: 0 | F33: =D33-E33 -> 400
A34: SEO | B34: Technical SEO (site speed, crawlability, schema markup) | C34: Monthly | D34: 350 | E34: 0 | F34: =D34-E34 -> 350
A35: SEO | B35: Local SEO (Google Business Profile, local citations, NAP consistency) | C35: Monthly | D35: 450 | E35: 0 | F35: =D35-E35 -> 450 | G35: Core fit for Revital's local-business client base
A36: SEO | B36: Off-Page SEO (link building, backlink outreach) | C36: Monthly | D36: 400 | E36: 0 | F36: =D36-E36 -> 400
A37: SEO | B37: Keyword Research & Strategy | C37: Monthly | D37: 200 | E37: 0 | F37: =D37-E37 -> 200
A38: SEO | B38: SEO Content Writing (blog posts, landing pages) | C38: Monthly | D38: 350 | E38: 0 | F38: =D38-E38 -> 350
A39: SEO | B39: SEO Audits | C39: One-Time Setup | D39: 500 | E39: 0 | F39: =D39-E39 -> 500
A40: SEO | B40: Google Search Console Management | C40: Monthly | D40: 150 | E40: 0 | F40: =D40-E40 -> 150
A41: SEO | B41: Rank Tracking & Reporting | C41: Monthly | D41: 150 | E41: 0 | F41: =D41-E41 -> 150
A42: Email Marketing | B42: Newsletter Campaigns | C42: Monthly | D42: 250 | E42: 0 | F42: =D42-E42 -> 250
A43: Email Marketing | B43: Promotional Emails | C43: Monthly | D43: 200 | E43: 0 | F43: =D43-E43 -> 200
A44: Email Marketing | B44: Drip / Nurture Sequences | C44: Monthly | D44: 300 | E44: 0 | F44: =D44-E44 -> 300
A45: Email Marketing | B45: Welcome Sequences | C45: Monthly | D45: 150 | E45: 0 | F45: =D45-E45 -> 150
A46: Email Marketing | B46: Re-engagement Campaigns | C46: Monthly | D46: 200 | E46: 0 | F46: =D46-E46 -> 200
A47: Email Marketing | B47: List Building & Growth | C47: One-Time Setup | D47: 300 | E47: 0 | F47: =D47-E47 -> 300
... A54: Website Design | B54: New Website Builds | C54: One-Time Setup | D54: 3500 | E54: 0 | F54: =D54-E54 -> 3500
A55: Website Design | B55: Website Redesigns | C55: Monthly | D55: 500 | E55: 0 | F55: =D55-E55 -> 500 | G55: Billed monthly for project duration
A56: Website Design | B56: Landing Page Design & Development | C56: One-Time Setup | D56: 600 | E56: 0 | F56: =D56-E56 -> 600
A57: Website Design | B57: Website Maintenance & Updates | C57: Monthly | D57: 150 | E57: 0 | F57: =D57-E57 -> 150
A58: Website Design | B58: UX/UI Optimization | C58: Monthly | D58: 300 | E58: 0 | F58: =D58-E58 -> 300
A59: Website Design | B59: Conversion Rate Optimization (CRO) | C59: Monthly | D59: 300 | E59: 0 | F59: =D59-E59 -> 300
A60: Website Design | B60: Speed & Performance Optimization | C60: Monthly | D60: 200 | E60: 0 | F60: =D60-E60 -> 200
A61: Website Design | B61: Mobile Responsiveness | C61: Monthly | D61: 150 | E61: 0 | F61: =D61-E61 -> 150
A62: Website Design | B62: Hosting & Domain Management | C62: Monthly | D62: 50 | E62: 0 | F62: =D62-E62 -> 50 | G62: Mostly pass-through + light markup
A63: Website Design | B63: Analytics Setup (GA4, Meta Pixel, GTM) | C63: One-Time Setup | D63: 300 | E63: 0 | F63: =D63-E63 -> 300
A64: Website Design | B64: E-commerce Setup (Shopify, WooCommerce) | C64: One-Time Setup | D64: 800 | E64: 0 | F64: =D64-E64 -> 800
A65: Website Design | B65: Platform Support: WordPress, Shopify, Webflow, Squarespace, Wix | C65: Monthly | D65: 150 | E65: 0 | F65: =D65-E65 -> 150
A66: Inbound Marketing | B66: Content Strategy Development | C66: One-Time Setup | D66: 500 | E66: 0 | F66: =D66-E66 -> 500
A67: Inbound Marketing | B67: Blog Writing & Management | C67: Monthly | D67: 300 | E67: 0 | F67: =D67-E67 -> 300
A68: Inbound Marketing | B68: Lead Magnet Creation (guides, checklists, templates, free audits) | C68: One-Time Setup | D68: 400 | E68: 0 | F68: =D68-E68 -> 400
A69: Inbound Marketing | B69: Landing Page Copywriting | C69: Monthly | D69: 250 | E69: 0 | F69: =D69-E69 -> 250
A70: Inbound Marketing | B70: Lead Capture Form Setup | C70: One-Time Setup | D70: 200 | E70: 0 | F70: =D70-E70 -> 200
A71: Inbound Marketing | B71: Marketing Funnel Build | C71: One-Time Setup | D71: 800 | E71: 0 | F71: =D71-E71 -> 800
A72: Inbound Marketing | B72: CTA Strategy | C72: Monthly | D72: 100 | E72: 0 | F72: =D72-E72 -> 100
A73: Inbound Marketing | B73: Content Distribution | C73: Monthly | D73: 200 | E73: 0 | F73: =D73-E73 -> 200
A74: Inbound Marketing | B74: Organic Lead Generation | C74: Monthly | D74: 300 | E74: 0 | F74: =D74-E74 -> 300
A75: Inbound Marketing | B75: Marketing Automation Setup | C75: One-Time Setup | D75: 600 | E75: 0 | F75: =D75-E75 -> 600
A76: Strategy | B76: Marketing Audit (full assessment of current marketing efforts) | C76: One-Time Setup | D76: 600 | E76: 0 | F76: =D76-E76 -> 600 | G76: Paid version of the free assessment used in cold outreach
A77: Strategy | B77: Competitor Analysis | C77: Monthly | D77: 250 | E77: 0 | F77: =D77-E77 -> 250
A78: Strategy | B78: Brand Positioning | C78: Monthly | D78: 400 | E78: 0 | F78: =D78-E78 -> 400
A79: Strategy | B79: Go-To-Market Strategy | C79: Monthly | D79: 500 | E79: 0 | F79: =D79-E79 -> 500
A80: Strategy | B80: Quarterly Marketing Planning | C80: Monthly | D80: 300 | E80: 0 | F80: =D80-E80 -> 300
A81: Strategy | B81: Campaign Strategy | C81: Monthly | D81: 300 | E81: 0 | F81: =D81-E81 -> 300
A82: Strategy | B82: KPI Framework Development | C82: One-Time Setup | D82: 400 | E82: 0 | F82: =D82-E82 -> 400
A83: Strategy | B83: Analytics & Data Interpretation | C83: Monthly | D83: 200 | E83: 0 | F83: =D83-E83 -> 200
A84: Strategy | B84: Marketing Roadmap Development | C84: One-Time Setup | D84: 500 | E84: 0 | F84: =D84-E84 -> 500
A85: Strategy | B85: Consulting & Advisory | C85: Monthly | D85: 250 | E85: 0 | F85: =D85-E85 -> 250
A86: Software & Tech Stack | B86: HubSpot Marketing Hub | C86: Monthly | D86: 75 | E86: 50 | F86: =D86-E86 -> 25 | G86: Cost = Starter tier + contacts allowance
A87: Software & Tech Stack | B87: Sprout Social Seat | C87: Monthly | D87: 249 | E87: 199 | F87: =D87-E87 -> 50 | G87: Cost = Standard plan, 1 seat
A88: Software & Tech Stack | B88: Klaviyo Base Plan | C88: Monthly | D88: 65 | E88: 45 | F88: =D88-E88 -> 20 | G88: Cost = entry tier, small contact list
A89: Branding & Design | B89: Brand Strategy Session | C89: One-Time Setup | D89: 300 | E89: 0 | F89: =D89-E89 -> 300 | G89: Discovery brief + positioning, small-biz tier
A90: Branding & Design | B90: Primary Logo Design | C90: One-Time Setup | D90: 600 | E90: 0 | F90: =D90-E90 -> 600 | G90: Freelance-tier primary mark, $500 most common reported figure
A91: Branding & Design | B91: Logo Variations & Submark | C91: One-Time Setup | D91: 250 | E91: 0 | F91: =D91-E91 -> 250 | G91: Icon/submark + alt lockups built on primary logo
A92: Branding & Design | B92: Color Palette & Typography System | C92: One-Time Setup | D92: 200 | E92: 0 | F92: =D92-E92 -> 200
A93: Branding & Design | B93: Brand Style Guide / Guidelines | C93: One-Time Setup | D93: 400 | E93: 0 | F93: =D93-E93 -> 400 | G93: Light style guide bundling logo, color, type
A94: Branding & Design | B94: Social Media Profile Graphics | C94: One-Time Setup | D94: 150 | E94: 0 | F94: =D94-E94 -> 150 | G94: Profile/cover images across platforms
A95: Branding & Design | B95: Branded Social Media Templates | C95: One-Time Setup | D95: 300 | E95: 0 | F95: =D95-E95 -> 300 | G95: Reusable post/story template set
A96: Branding & Design | B96: Business Card / Promotional Design | C96: One-Time Setup | D96: 150 | E96: 0 | F96: =D96-E96 -> 150

Sheet Category Summary
A1: Category | B1: # Services | C1: Sum of Suggested Monthly Prices ($) | D1: Sum of Suggested One-Time Setup Prices ($)
A2: Organic Social | B2: =COUNTIF('Price Sheet'!A:A,A2) -> 8 | C2: =SUMIFS('Price Sheet'!D:D,'Price Sheet'!A:A,A2,'Price Sheet'!C:C,"Monthly") -> 1700 | D2: =SUMIFS('Price Sheet'!D:D,'Price Sheet'!A:A,A2,'Price Sheet'!C:C,"One-Time Setup") -> 0
A3: Paid Social | B3: =COUNTIF('Price Sheet'!A:A,A3) -> 11 | C3: =SUMIFS('Price Sheet'!D:D,'Price Sheet'!A:A,A3,'Price Sheet'!C:C,"Monthly") -> 3450 | D3: =SUMIFS('Price Sheet'!D:D,'Price Sheet'!A:A,A3,'Price Sheet'!C:C,"One-Time Setup") -> 500
A4: Paid Search | B4: =COUNTIF('Price Sheet'!A:A,A4) -> 10 | C4: =SUMIFS('Price Sheet'!D:D,'Price Sheet'!A:A,A4,'Price Sheet'!C:C,"Monthly") -> 3200 | D4: =SUMIFS('Price Sheet'!D:D,'Price Sheet'!A:A,A4,'Price Sheet'!C:C,"One-Time Setup") -> 350
A5: SEO | B5: =COUNTIF('Price Sheet'!A:A,A5) -> 9 | C5: =SUMIFS('Price Sheet'!D:D,'Price Sheet'!A:A,A5,'Price Sheet'!C:C,"Monthly") -> 2450 | D5: =SUMIFS('Price Sheet'!D:D,'Price Sheet'!A:A,A5,'Price Sheet'!C:C,"One-Time Setup") -> 500
A6: Email Marketing | B6: =COUNTIF('Price Sheet'!A:A,A6) -> 12 | C6: =SUMIFS('Price Sheet'!D:D,'Price Sheet'!A:A,A6,'Price Sheet'!C:C,"Monthly") -> 1900 | D6: =SUMIFS('Price Sheet'!D:D,'Price Sheet'!A:A,A6,'Price Sheet'!C:C,"One-Time Setup") -> 700
A7: Website Design | B7: =COUNTIF('Price Sheet'!A:A,A7) -> 12 | C7: =SUMIFS('Price Sheet'!D:D,'Price Sheet'!A:A,A7,'Price Sheet'!C:C,"Monthly") -> 1800 | D7: =SUMIFS('Price Sheet'!D:D,'Price Sheet'!A:A,A7,'Price Sheet'!C:C,"One-Time Setup") -> 5200
A8: Inbound Marketing | B8: =COUNTIF('Price Sheet'!A:A,A8) -> 10 | C8: =SUMIFS('Price Sheet'!D:D,'Price Sheet'!A:A,A8,'Price Sheet'!C:C,"Monthly") -> 1150 | D8: =SUMIFS('Price Sheet'!D:D,'Price Sheet'!A:A,A8,'Price Sheet'!C:C,"One-Time Setup") -> 2500
A9: Strategy | B9: =COUNTIF('Price Sheet'!A:A,A9) -> 10 | C9: =SUMIFS('Price Sheet'!D:D,'Price Sheet'!A:A,A9,'Price Sheet'!C:C,"Monthly") -> 2200 | D9: =SUMIFS('Price Sheet'!D:D,'Price Sheet'!A:A,A9,'Price Sheet'!C:C,"One-Time Setup") -> 1500
A10: Software & Tech Stack | B10: =COUNTIF('Price Sheet'!A:A,A10) -> 3 | C10: =SUMIFS('Price Sheet'!D:D,'Price Sheet'!A:A,A10,'Price Sheet'!C:C,"Monthly") -> 389 | D10: =SUMIFS('Price Sheet'!D:D,'Price Sheet'!A:A,A10,'Price Sheet'!C:C,"One-Time Setup") -> 0
A11: Branding & Design | B11: =COUNTIF('Price Sheet'!A:A,A11) -> 8 | C11: =SUMIFS('Price Sheet'!D:D,'Price Sheet'!A:A,A11,'Price Sheet'!C:C,"Monthly") -> 0 | D11: =SUMIFS('Price Sheet'!D:D,'Price Sheet'!A:A,A11,'Price Sheet'!C:C,"One-Time Setup") -> 2350
A12: TOTAL | B12: =SUM(B2:B11) -> 93 | C12: =SUM(C2:C11) -> 18239 | D12: =SUM(D2:D11) -> 13600

Sheet Sources
A1: Benchmark sources used for these suggested starting prices (small-business / local-agency tier, July 2026):
A3: • Social media management pricing — LYFE Marketing, Sprout Social, RecurPost (small biz tier $500-2,000/mo)
A4: • Paid social ad management fees — Webtonic, Stackmatix (mgmt fee separate from ad spend, 10-20% of spend or flat fee)
A5: • Google Ads / PPC management pricing — AMW, Outerbox Design, ALM Corp (small biz tier $500-1,500/mo)
A6: • Local SEO pricing — SEOProfy, Arc4, MultiWebTeam (small biz tier $500-1,500/mo, most common band)
A7: • Email marketing management pricing — Nutshell, AMW, Anthem Software (small biz tier $500-2,000/mo)
A8: • Website design cost — Levitate, GruffyGoat, OneLittleWeb (small biz builds $2,000-8,000)
A9: • HubSpot Marketing Hub pricing — MailSoftly, SendX ($20/seat/mo Starter + contact tiers)
A10: • Sprout Social pricing — Ampifire, CostBench ($199/mo Standard plan)
A11: • Klaviyo pricing — SendX, Omnisend ($20-45/mo entry tier by list size)
A12: • Logo & brand identity pricing — logomakerr.ai, manypixels.co, wearetenet.com (freelance tier $300-2,000; brand identity packages $2,500+ for larger studios/agencies)
